README.md
setup.py
ssafy/__init__.py
ssafy/cli.py
ssafy.egg-info/PKG-INFO
ssafy.egg-info/SOURCES.txt
ssafy.egg-info/dependency_links.txt
ssafy.egg-info/entry_points.txt
ssafy.egg-info/top_level.txt